tapioca_crunchbase/__init__.py
tapioca_crunchbase/resource_mapping.py
tapioca_crunchbase/tapioca_crunchbase.py
tapioca_crunchbase-0.1.dist-info/DESCRIPTION.rst
tapioca_crunchbase-0.1.dist-info/METADATA
tapioca_crunchbase-0.1.dist-info/RECORD
tapioca_crunchbase-0.1.dist-info/WHEEL
tapioca_crunchbase-0.1.dist-info/metadata.json
tapioca_crunchbase-0.1.dist-info/pbr.json
tapioca_crunchbase-0.1.dist-info/top_level.txt
