Metadata-Version: 2.0
Name: tapioca-crunchbase
Version: 0.1
Summary: crunchbase API wrapper using tapioca
Home-page: https://github.com/vu3jej/tapioca-crunchbase
Author: Jithesh E J
Author-email: mail@jithesh.net
License: MIT
Keywords: crunchbase
Platform: UNKNOWN
Classifier: Development Status :: 5 - Production/Stable
Classifier: Intended Audience :: Developers
Classifier: License :: OSI Approved :: MIT License
Classifier: Natural Language :: English
Classifier: Programming Language :: Python :: 2
Classifier: Programming Language :: Python :: 2.7
Classifier: Programming Language :: Python :: 3
Classifier: Programming Language :: Python :: 3.1
Classifier: Programming Language :: Python :: 3.2
Classifier: Programming Language :: Python :: 3.3
Classifier: Programming Language :: Python :: 3.4
Requires-Dist: tapioca-wrapper (<0.7.0)
